odoo/addons/l10n_pt_stock_invoicexpress/README.rst
odoo/addons/l10n_pt_stock_invoicexpress/__init__.py
odoo/addons/l10n_pt_stock_invoicexpress/__manifest__.py
odoo/addons/l10n_pt_stock_invoicexpress/data/mail_template.xml
odoo/addons/l10n_pt_stock_invoicexpress/i18n/l10n_pt_stock_invoicexpress.pot
odoo/addons/l10n_pt_stock_invoicexpress/i18n/pt.po
odoo/addons/l10n_pt_stock_invoicexpress/models/__init__.py
odoo/addons/l10n_pt_stock_invoicexpress/models/res_company.py
odoo/addons/l10n_pt_stock_invoicexpress/models/res_config_settings.py
odoo/addons/l10n_pt_stock_invoicexpress/models/res_partner.py
odoo/addons/l10n_pt_stock_invoicexpress/models/stock_picking.py
odoo/addons/l10n_pt_stock_invoicexpress/models/stock_picking_type.py
odoo/addons/l10n_pt_stock_invoicexpress/readme/CONFIGURE.rst
odoo/addons/l10n_pt_stock_invoicexpress/readme/CONTRIBUTORS.rst
odoo/addons/l10n_pt_stock_invoicexpress/readme/DESCRIPTION.rst
odoo/addons/l10n_pt_stock_invoicexpress/readme/USAGE.rst
odoo/addons/l10n_pt_stock_invoicexpress/static/description/cover.png
odoo/addons/l10n_pt_stock_invoicexpress/static/description/icon.png
odoo/addons/l10n_pt_stock_invoicexpress/static/description/index.html
odoo/addons/l10n_pt_stock_invoicexpress/tests/__init__.py
odoo/addons/l10n_pt_stock_invoicexpress/tests/test_invoicexpress.py
odoo/addons/l10n_pt_stock_invoicexpress/views/res_company_view.xml
odoo/addons/l10n_pt_stock_invoicexpress/views/res_config_settings.xml
odoo/addons/l10n_pt_stock_invoicexpress/views/stock_picking_type_view.xml
odoo/addons/l10n_pt_stock_invoicexpress/views/stock_picking_view.xml
odoo14_addon_l10n_pt_stock_invoicexpress-14.0.3.0.2.dist-info/METADATA
odoo14_addon_l10n_pt_stock_invoicexpress-14.0.3.0.2.dist-info/WHEEL
odoo14_addon_l10n_pt_stock_invoicexpress-14.0.3.0.2.dist-info/top_level.txt
odoo14_addon_l10n_pt_stock_invoicexpress-14.0.3.0.2.dist-info/RECORD
