Metadata-Version: 2.1
Name: odoo14-addon-l10n-pt-stock-invoicexpress
Version: 14.0.3.0.2
Summary: Portuguese legal transport and shipping documents (Guias de Transporte e Guias de Remessa) generated with InvoiceXpress
Home-page: https://github.com/OCA/l10n-portugal
Author: Open Source Integrators, Odoo Community Association (OCA)
Author-email: support@odoo-community.org
License: AGPL-3
Platform: UNKNOWN
Classifier: Programming Language :: Python
Classifier: Framework :: Odoo
Classifier: Framework :: Odoo :: 14.0
Classifier: License :: OSI Approved :: GNU Affero General Public License v3
Classifier: Development Status :: 5 - Production/Stable
Requires-Python: >=3.6
Requires-Dist: odoo14-addon-l10n-pt-account-invoicexpress
Requires-Dist: odoo <14.1dev,>=14.0a
